README.md
setup.py
ptool/__init__.py
ptool/__main__.py
ptool/arg_util.py
ptool/commands.py
ptool/config.py
ptool/exceptions.py
ptool/file_info.py
ptool/git_util.py
ptool/lang_util.py
ptool/project_yaml.py
ptool/template_spec.py
ptool/template_util.py
ptool/util.py
ptool/value_source.py
ptool.egg-info/PKG-INFO
ptool.egg-info/SOURCES.txt
ptool.egg-info/dependency_links.txt
ptool.egg-info/entry_points.txt
ptool.egg-info/not-zip-safe
ptool.egg-info/requires.txt
ptool.egg-info/top_level.txt