Metadata-Version: 1.1
Name: ptool
Version: 0.5
Summary: Skeleton project generator for various programming languages
Home-page: https://github.com/rcook/ptool
Author: Richard Cook
Author-email: rcook@rcook.org
License: MIT
Platform: UNKNOWN
Classifier: Development Status :: 3 - Alpha
Classifier: License :: OSI Approved :: MIT License
Classifier: Programming Language :: Python :: 2.7
